{
    "status": "ok",
    "totalResults": 70,
    "articles": [
        {
          "source": {
            "id": "espn-cric-info",
            "name": "ESPN Cric Info"
          },
          "author": "ESPNcricinfo staff",
          "title": "Litton to lead Bangladesh in ODI series against India - ESPNcricinfo",
          "description": "Regular captain Tamim Iqbal has pulled out of the series because of a groin injury",
          "url": "https://www.espncricinfo.com/story/ban-vs-ind-odi-series-litton-das-to-captain-bangladesh-for-india-odis-in-tamim-iqbals-absence-1347851",
          "urlToImage": "https://img1.hscicdn.com/image/upload/f_auto/lsci/db/PICTURES/CMS/348600/348654.6.jpg",
          "publishedAt": "2022-12-02T12:59:32Z",
          "content": "Litton Das has not captained Bangladesh in an ODI previously  •  Associated Press"
        },
        {
          "source": {
            "id": null,
            "name": "NDTV News"
          },
          "author": null,
          "title": "\"Love Is Love\": Dutee Chand's Instagram Post With Partner - NDTV",
          "description": "Star athlete Dutee Chand has posted a photo on Instagram with her partner, Monalisa, both wearing celebratory attire.",
          "url": "https://www.ndtv.com/india-news/love-is-love-dutee-chands-instagram-post-with-partner-monalisa-3572651",
          "urlToImage": "https://c.ndtvimg.com/2022-12/0qv9r5p_dutee-chand_625x300_02_December_22.jpg",
          "publishedAt": "2022-12-02T12:13:35Z",
          "content": "Dutee Chand, 24, and Monalisa took the photo at the wedding of the star athlete's sister\r\nNew Delhi: Star athlete Dutee Chand has posted a photo on Instagram with her partner, Monalisa, both wearing … [+1165 chars]"
        },
        {
          "source": {
            "id": "espn-cric-info",
            "name": "ESPN Cric Info"
          },
          "author": "Danyal Rasool",
          "title": "PCB chairman slams Rawalpindi pitch as 'embarrassing' as bowlers toil in Test - ESPNcricinfo",
          "description": "Ramiz Raja warns that the country is paying price for lengthy exile from international cricket",
          "url": "https://www.espncricinfo.com/story/pakistan-vs-england-1st-test-rawalpindi-pcb-chairman-slams-rawalpindi-pitch-as-embarrassing-as-bowlers-toil-in-tes-1347848",
          "urlToImage": "https://img1.hscicdn.com/image/upload/f_auto/lsci/db/PICTURES/CMS/350100/350124.6.jpg",
          "publishedAt": "2022-12-02T12:12:29Z",
          "content": "Imam-ul-Haq was untroubled in Pakistan's reply, as England took their turn to toil in the field  •  AFP/Getty Images"
        },
        {
          "source": {
            "id": null,
            "name": "NDTV News"
          },
          "author": "NDTV Sports Desk",
          "title": "Ricky Ponting Rushed To Hospital After Suffering Health Scare On Day 3 Of Australia vs West Indies T.. - NDTV Sports",
          "description": "Former Australian batting great and captain Ricky Ponting has been rushed to the hospital due to a health scare, according to reports in several Australian media outlets.",
          "url": "https://sports.ndtv.com/cricket/ricky-ponting-rushed-to-hospital-after-suffering-health-scare-on-day-3-of-australia-vs-west-indies-test-reports-3571967",
          "urlToImage": "https://c.ndtvimg.com/2022-04/obugj4v8_ricky-ponting-bcciipl_625x300_27_April_22.jpg?im=FeatureCrop,algorithm=dnn,width=1200,height=675",
          "publishedAt": "2022-12-02T11:11:00Z",
          "content": "Former Australian batting great and captain Ricky Ponting has been rushed to the hospital due to a health scare, according to reports in several Australian media outlets. Ponting was commentating for… [+1603 chars]"
        },
        {
          "source": {
            "id": null,
            "name": "Pundit Feed"
          },
          "author": null,
          "title": "World Cup 2022: England full-back hits out at ‘lazy’ critics who say he can’t defend - Pundit Feed",
          "description": "England have been drawn against Senegal in the 2022 World Cup Round of 16 after topping Group B with two wins and a draw.",
          "url": "https://punditfeed.com/sports-news/football/world-cup-2022-england-full-back-hits-out-at-lazy-critics-who-say-he-cant-defend/",
          "urlToImage": "https://punditfeed.com/wp-admin/admin-ajax.php?action=rank_math_overlay_thumb&id=158101&type=play&secret=398175e540cd2065916c7d7d24d12ef8",
          "publishedAt": "2022-12-02T11:01:19Z",
          "content": "UK: 18+ USA: 21+ | Begambleaware.org  | T&amp;Cs apply | Play Responsibly\r\nEngland defender Trent Alexander-Arnold has hit out at the lazy critics who question his defensive abilities.\r\nWhile the Liv… [+2843 chars]"
        },
        {
          "source": {
            "id": "marca",
            "name": "Marca"
          },
          "author": "JON PRADA, adapted by SAM",
          "title": "Germany cries out against Japan's goal, comparing it to Hurst's in 1966 - Marca English",
          "description": "Germany&apos;s elimination from the group stage for the second consecutive World Cup was not only brought on by the 2014 World champions being beaten.\n\nIn Germany, media outlets, n",
          "url": "https://www.marca.com/en/world-cup/2022/12/02/6389c93e22601d7e5a8b4568.html",
          "urlToImage": "https://phantom-marca.unidadeditorial.es/d9e0b4cd145bfed792a6e7d95e7638b6/resize/1200/f/jpg/assets/multimedia/imagenes/2022/12/01/16699322541946.jpg",
          "publishedAt": "2022-12-02T09:58:27Z",
          "content": "Germany's elimination from the group stage for the second consecutive World Cup was not only brought on by the 2014 World champions being beaten.\r\nIn Germany, media outlets, namely Bild, analysed the… [+1487 chars]"
        },
        {
          "source": {
            "id": "google-news",
            "name": "Google News"
          },
          "author": null,
          "title": "'The Hand of the Devil' and why the Ghana-Uruguay game is such a big deal - The Indian Express",
          "description": null,
          "url": "https://news.google.com/__i/rss/rd/articles/CBMifGh0dHBzOi8vaW5kaWFuZXhwcmVzcy5jb20vYXJ0aWNsZS9leHBsYWluZWQvdGhlLWhhbmQtb2YtdGhlLWRldmlsLWFuZC13aHktdGhlLWdoYW5hLXVydWd1YXktZ2FtZS1pcy1zdWNoLWEtYmlnLWRlYWwtODMwMjQxNC_SAQA?oc=5",
          "urlToImage": null,
          "publishedAt": "2022-12-02T09:28:30Z",
          "content": null
        },
        {
          "source": {
            "id": null,
            "name": "Crictracker.com"
          },
          "author": "Kshitij Kumar",
          "title": "Bangladesh vs India ODI series: India's Predicted Playing XI - CricTracker",
          "description": "India have announced a 17-member squad for the ODI series against the Bangla Tigers, which starts on December 4. The senior trio of Rohit Sharma, KL Rahul, and Virat Kohli have returned to the interna",
          "url": "https://www.crictracker.com/cricket-appeal/bangladesh-vs-india-odi-series-indias-predicted-playing-xi/",
          "urlToImage": "https://media.crictracker.com/media/attachments/1667708100451_FotoJet-(33).jpeg",
          "publishedAt": "2022-12-02T09:16:00Z",
          "content": "India have announced a 17-member squad for the ODI series against the Bangla Tigers, which starts on December 4. The senior trio of Rohit Sharma, KL Rahul, and Virat Kohli have returned to the intern… [+1724 chars]"
        },
        {
          "source": {
            "id": null,
            "name": "India TV News"
          },
          "author": "Written by Jishu Bhattacharya",
          "title": "Dwayne Bravo retires from IPL, will continue his association with Chennai Super Kings in 'THIS' role - India TV News",
          "description": "Dwayne Bravo, the Chennai Super Kings stalwart has called time on his IPL career but his journey with the franchise will continue in a new role. Bravo started his legendary association with the MS Dhoni-led team in 2011",
          "url": "https://www.indiatvnews.com/sports/cricket/dwayne-bravo-retires-from-ipl-will-continue-his-association-with-chennai-super-kings-in-this-role-bowling-coach-2023-2022-12-02-828165",
          "urlToImage": "https://resize.indiatvnews.com/en/resize/newbucket/1200_-/2022/04/PTI04_21_2022_000251B.jpg",
          "publishedAt": "2022-12-02T09:09:05Z",
          "content": "After his best mate Kieron Pollard, now Dwayne Bravo has called time on his Indian Premier League career. Bravo debuted in the inaugural edition of the IPL in 2008 and started his journey with the me… [+1574 chars]"
        },
        {
          "source": {
            "id": null,
            "name": "NDTV News"
          },
          "author": null,
          "title": "Watch: Hilarious DRS Call During Gully Cricket Bowls Over Spinner Ashwin - NDTV",
          "description": "They say cricket is an Indian game accidentally discovered by the British.' After all, cricket is not just a game but an emotion in India. Be it gully cricket or cheering our favourite players, fans love to celebrate the sport,",
          "url": "https://www.ndtv.com/offbeat/watch-this-hilarious-drs-call-during-a-gully-cricket-game-has-ashwin-s-attention-3568911",
          "urlToImage": "https://c.ndtvimg.com/2022-12/c24k2al_cricket_625x300_02_December_22.jpg",
          "publishedAt": "2022-12-02T08:52:38Z",
          "content": "People have called it the \"best DRS method\".\r\nNew Delhi: They say cricket is an Indian game accidentally discovered by the British.' After all, cricket is not just a game but an emotion in India. Be … [+2307 chars]"
        },
        {
          "source": {
            "id": null,
            "name": "Hindustan Times"
          },
          "author": "HT Sports Desk",
          "title": "'To hell with them. I don't have time for this': Ravi Shastri on Kohli vs Rohit - Hindustan Times",
          "description": "Ravi Shastri has in the past been flooded with numerous Virat Kohli vs Rohit Sharma debate but this time around, the former India coach came up with a rather unexpected response. | Cricket",
          "url": "https://www.hindustantimes.com/cricket/to-hell-with-them-i-don-t-have-time-for-this-ravi-shastri-s-hard-hitting-take-on-virat-kohli-vs-rohit-sharma-debate-101669968583728.html",
          "urlToImage": "https://images.hindustantimes.com/img/2022/12/02/1600x900/shastri-kohli-rohit-getty_1669968835607_1669968839789_1669968839789.jpg",
          "publishedAt": "2022-12-02T08:18:39Z",
          "content": "If there is one person who has endlessly addressed the numerous Virat Kohli vs Rohit Sharma debates, it is former India coach Ravi Shastri. When he was in charge as Team India's head coach, reports o… [+2480 chars]"
        },
        {
          "source": {
            "id": null,
            "name": "NDTV News"
          },
          "author": "NDTV Sports Desk",
          "title": "\"I Have Seen Everything\": Wasim Akram's Brilliant Reaction To England's 500 in 74 Overs - NDTV Sports",
          "description": "England dominated the hapless Pakistan bowling, reaching 506/4 when Harry Brook reached 101. Earlier, Ollie Pope had scored 108 Crawley had amassed 122 and Duckett 107.",
          "url": "https://sports.ndtv.com/cricket/i-have-seen-everything-wasim-akrams-brilliant-reaction-to-englands-500-in-74-overs-3570688",
          "urlToImage": "https://c.ndtvimg.com/2022-09/uob7t9b_wasim-akram_625x300_07_September_22.jpg?im=FeatureCrop,algorithm=dnn,width=1200,height=675",
          "publishedAt": "2022-12-02T08:04:18Z",
          "content": "The England cricket team shattered cricketing records by hammering 500 runs on the Day 1 of the first Test against Pakistan in Rawalpindi. Bazz-ball' was in full swing as the likes of Zak Crawley, Be… [+2024 chars]"
        },
        {
          "source": {
            "id": null,
            "name": "Chess.com"
          },
          "author": "Venkatachalam Saravanan",
          "title": "Nihal, Ushenina Winners In Contrasting Styles - Chess.com",
          "description": "GM Nihal Sarin won the 2022 Tata Steel Chess India Open Rapid with a round to spare, while GM Anna Ushenina tied for first and won the tiebreak match to win the Women's Rapid section.",
          "url": "https://www.chess.com/news/view/2022-tata-steel-chess-india-rapid-day-3",
          "urlToImage": "https://images.chesscomfiles.com/uploads/v1/news/1126955.3ff49f5b.5000x5000o.f605f0d40999.png",
          "publishedAt": "2022-12-02T06:46:00Z",
          "content": "GM Nihal Sarin won the 2022 Tata Steel Chess India Open Rapid with a round to spare, while GM Anna Ushenina tied for first and won the tiebreak match to win the 2022 Tata Steel Chess India Women's Ra… [+9057 chars]"
        },
        {
          "source": {
            "id": null,
            "name": "NDTV News"
          },
          "author": "Agence France-Presse",
          "title": "Germany's World Cup Elimination \"Like A Horror Movie\": Kai Havertz - NDTV Sports",
          "description": "Germany forward Kai Havertz compared his side's World Cup elimination to \"watching a horror movie\", with the team discovering their fate when the result of the game between Japan and Spain was displayed in the stadium.",
          "url": "https://sports.ndtv.com/fifa-world-cup-2022/germanys-world-cup-elimination-like-a-horror-movie-kai-havertz-3571483",
          "urlToImage": "https://c.ndtvimg.com/2022-12/omjohs5o_kai-havertz-afp_625x300_02_December_22.jpg?im=FeatureCrop,algorithm=dnn,width=1200,height=675",
          "publishedAt": "2022-12-02T06:29:20Z",
          "content": "Germany forward Kai Havertz compared his side's World Cup elimination to \"watching a horror movie\", with the team discovering their fate when the result of the game between Japan and Spain was displa… [+1345 chars]"
        },
        {
          "source": {
            "id": null,
            "name": "Hindustan Times"
          },
          "author": "HT Sports Desk",
          "title": "Watch: Naseem Shah's roaring revenge after Stokes slams him for first-ball six - Hindustan Times",
          "description": "The first over of the second day's play was, however, as much about Ben Stokes's audacity as Naseem Shah's presence of mind. After being shell-shocked straight over the back of his head in the first ball, the talented Pakistan right-arm pacer came back strong…",
          "url": "https://www.hindustantimes.com/cricket/watch-naseem-shah-s-roaring-revenge-after-ben-stokes-slams-him-for-first-ball-six-on-day-2-of-pak-vs-eng-1st-test-101669962071540.html",
          "urlToImage": "https://images.hindustantimes.com/img/2022/12/02/1600x900/naseem_stokes_1669962289933_1669962300502_1669962300502.JPG",
          "publishedAt": "2022-12-02T06:28:53Z",
          "content": "England carried their brutal assault on Pakistan with captain Ben Stokes charging down the track to hit pacer Naseem Shah for a six off the first ball he faced on Day 2 of the first Test in Rawalpind… [+1816 chars]"
        },
        {
          "source": {
            "id": null,
            "name": "NDTV News"
          },
          "author": "Agence France-Presse",
          "title": "Samurai Spirit: Japan Explodes With World Cup Joy - NDTV Sports",
          "description": "As the final whistle blew on Japan's shock victory over Spain, thrilled fans flooded onto Tokyo's Shibuya Scramble crossing to celebrate a win few had dared to dream of.",
          "url": "https://sports.ndtv.com/fifa-world-cup-2022/samurai-spirit-japan-explodes-with-world-cup-joy-3571415",
          "urlToImage": "https://c.ndtvimg.com/2022-12/bibblis8_japan-players-afp_625x300_02_December_22.jpg?im=FeatureCrop,algorithm=dnn,width=1200,height=675",
          "publishedAt": "2022-12-02T06:08:43Z",
          "content": "As the final whistle blew on Japan's shock victory over Spain, thrilled fans flooded onto Tokyo's Shibuya Scramble crossing to celebrate a win few had dared to dream of. \"Japan, bravo! Japan, bravo!\"… [+2822 chars]"
        },
        {
          "source": {
            "id": null,
            "name": "cricket.com.au"
          },
          "author": "Adam Burnett",
          "title": "History makers: Fab four breaks new Test ground - cricket.com.au",
          "description": "Champions on the field, this Baggy Green bowling quartet are also long-time friends off it. They share the factors that make their bond so special",
          "url": "https://www.cricket.com.au/news/feature/pat-cummins-josh-hazlewood-nathan-lyon-mitchell-starc-200-wickets-test-record-australia-west-indies/2022-12-02",
          "urlToImage": "https://www.cricket.com.au/~/-/media/News/2022/12/29big_four_main.ashx?w=1600",
          "publishedAt": "2022-12-02T05:29:04Z",
          "content": "Bowling quartet chuffed when told new record: Lyon\r\nOne by one, they file in, more than 1100 Test wickets between them. Polite to a man, they're all also quite talkative, despite this interview being… [+14742 chars]"
        },
        {
          "source": {
            "id": null,
            "name": "PlanetF1"
          },
          "author": "Henry Valantine",
          "title": "Mika Hakkinen doubts Max Verstappen will continuing dominating F1 in 2023 - Planet F1",
          "description": "Max Verstappen was truly dominant in 2022, but keeping it up next year will not be easy.",
          "url": "https://www.planetf1.com/news/mika-hakkinen-max-verstappen-dominance-not-straightforward/",
          "urlToImage": "https://d3cm515ijfiu6w.cloudfront.net/wp-content/uploads/2022/10/11123600/max-verstappen-trophy-hold-suzuka-2022-planetf1.jpg",
          "publishedAt": "2022-12-02T05:01:57Z",
          "content": "Mika Hakkinen believes it will not be a “straightforward” task for Max Verstappen to maintain the level of dominance he showed in 2022, given the chances others will have to close the gap.\r\nVerstappe… [+2162 chars]"
        },
        {
          "source": {
            "id": null,
            "name": "NDTV News"
          },
          "author": "Press Trust of India",
          "title": "\"Would Have Felt Hurt If Hardik Pandya Or DK Hit Me For Sixes But Kohli...\": Haris Rauf's Ultimate P.. - NDTV Sports",
          "description": "Haris Rauf believes that no player in world cricket save the peerless Virat Kohli could have hit him for those two sixes in that thrilling India victory against Pakistan in the T20 World Cup match in October.",
          "url": "https://sports.ndtv.com/cricket/would-have-felt-hurt-if-hardik-pandya-or-dk-hit-me-for-sixes-but-kohli-haris-raufs-ultimate-praise-3571167",
          "urlToImage": "https://c.ndtvimg.com/2022-12/1orh0sg_virat-kohli-instagram_625x300_02_December_22.jpg",
          "publishedAt": "2022-12-02T04:32:00Z",
          "content": "Haris Rauf believes that no player in world cricket save the peerless Virat Kohli could have hit him for those two sixes in that thrilling India victory against Pakistan in the T20 World Cup match in… [+2546 chars]"
        },
        {
          "source": {
            "id": null,
            "name": "International Cricket Council"
          },
          "author": "ICC",
          "title": "Key Aussie all-rounder to miss summer, in doubt for India tour - ICC Cricket",
          "description": "Another key member in Australia's playing group will miss the summer of cricket Down Under through injury.",
          "url": "https://www.icc-cricket.com/news/2975214",
          "urlToImage": "https://resources.pulse.icc-cricket.com/ICC/photo/2022/12/02/944791e3-52fe-4358-91d5-cbe5edaebb2b/Mitchell-Marsh.png",
          "publishedAt": "2022-12-02T04:31:20Z",
          "content": "Another key member in Australia's playing group will miss the summer of cricket Down Under through injury.Mitchell Marsh has elected to undergo surgery on his ankle in a bid to be fit for next year's… [+1624 chars]"
        }
      ]
    }
